pyroll/export/__init__.py
pyroll/export/cli.py
pyroll/export/convert.py
pyroll/export/export.py
pyroll/export/hookspecs.py
pyroll/export/pluggy.py
pyroll_export-3.0.0.dist-info/METADATA
pyroll_export-3.0.0.dist-info/WHEEL
pyroll_export-3.0.0.dist-info/entry_points.txt
pyroll_export-3.0.0.dist-info/licenses/LICENSE
pyroll_export-3.0.0.dist-info/RECORD
